_chips_c.cpython-310-x86_64-linux-gnu.so
chips_c.py
Chips_python-2.2.3.data/scripts/c2verilog
Chips_python-2.2.3.data/scripts/csim
chips/__init__.py
chips/utils/debugger.py
chips/utils/gui_instance.py
chips/utils/block_diagram.py
chips/utils/gui_report.py
chips/utils/__init__.py
chips/utils/icons/into.png
chips/utils/icons/reset.png
chips/utils/icons/reset_disabled.png
chips/utils/icons/over_disabled.png
chips/utils/icons/stop_disabled.png
chips/utils/icons/run.png
chips/utils/icons/tick.png
chips/utils/icons/into_disabled.png
chips/utils/icons/tick_disabled.png
chips/utils/icons/run_disabled.png
chips/utils/icons/stop.png
chips/utils/icons/over.png
chips/chipsweb/webapp.py
chips/chipsweb/examples.py
chips/chipsweb/__init__.py
chips/chipsweb/templates/page.html
chips/api/api.py
chips/api/__init__.py
chips/components/components.py
chips/components/__init__.py
chips/compiler/parser.py
chips/compiler/exceptions.py
chips/compiler/optimizer.py
chips/compiler/allocator.py
chips/compiler/python_model.py
chips/compiler/fpu.py
chips/compiler/utils.py
chips/compiler/profiler.py
chips/compiler/register_map.py
chips/compiler/types.py
chips/compiler/verilog_area.py
chips/compiler/macro_expander.py
chips/compiler/builtins.h
chips/compiler/parse_tree.py
chips/compiler/compiler.py
chips/compiler/__init__.py
chips/compiler/tokens.py
chips/compiler/instruction_utils.py
chips/compiler/include/string.h
chips/compiler/include/scan.h
chips/compiler/include/errno.h
chips/compiler/include/stdio.h
chips/compiler/include/ctype.h
chips/compiler/include/time.h
chips/compiler/include/math.h
chips/compiler/include/stdlib.h
chips/compiler/include/print.h
Chips_python-2.2.3.dist-info/COPYING.txt
Chips_python-2.2.3.dist-info/top_level.txt
Chips_python-2.2.3.dist-info/WHEEL
Chips_python-2.2.3.dist-info/METADATA
Chips_python-2.2.3.dist-info/RECORD
