Metadata-Version: 2.1
Name: Chips-python
Version: 2.2.3
Summary: Design hardware with Python
Home-page: http://benfre.github.io/Chips/
Download-URL: http://github.com/benfre/Chips
Author: Jon Dawson
Author-email: chips@jondawson.org.uk
Keywords: Verilog,FPGA,C,HDL,Synthesis,VHDL
Classifier: Programming Language :: Python
Classifier: License :: OSI Approved :: MIT License
Classifier: Operating System :: OS Independent
Classifier: Intended Audience :: Science/Research
Classifier: Intended Audience :: Developers
Classifier: Development Status :: 3 - Alpha
Classifier: Topic :: Scientific/Engineering :: Electronic Design Automation (EDA)
Classifier: Topic :: Software Development :: Embedded Systems
Classifier: Topic :: Software Development :: Code Generators
License-File: COPYING.txt
Requires-Dist: numpy
